gps_encoding-1.5.4.dist-info/METADATA
gps_encoding-1.5.4.dist-info/WHEEL
gps_encoding/__init__.py
gps_encoding/gps_encoding.cpython-36m-x86_64-linux-gnu.so
gps_encoding-1.5.4.dist-info/RECORD
