Metadata-Version: 2.1
Name: gps_encoding
Version: 1.5.4
Keywords: gps,encode,decode
Home-Page: https://github.com/rphlo/gps_encoding
Author: Raphael Stefanini <raphael@rphlo.com>
Author-email: Raphael Stefanini <raphael@rphlo.com>
License: MIT
Project-URL: Source Code, https://github.com/rphlo/gps_enoding.git
